<annotation><folder>open_images_volume</folder><filename>0bea1d5e22537805.jpg</filename><path>/mnt/open_images_volume/0bea1d5e22537805.jpg</path><source><database>Unknown</database></source><size><width>696</width><height>1024</height><depth>3</depth></size><segmented>0</segmented><object><name>Fish</name><pose>Unspecified</pose><truncated>0</truncated><difficult>0</difficult><bndbox><xmin>183</xmin><ymin>595</ymin><xmax>512</xmax><ymax>824</ymax></bndbox></object><object><name>Fish</name><pose>Unspecified</pose><truncated>0</truncated><difficult>0</difficult><bndbox><xmin>196</xmin><ymin>275</ymin><xmax>504</xmax><ymax>542</ymax></bndbox></object><object><name>Fish</name><pose>Unspecified</pose><truncated>0</truncated><difficult>0</difficult><bndbox><xmin>281</xmin><ymin>84</ymin><xmax>401</xmax><ymax>189</ymax></bndbox></object></annotation>